Workbook
Name DNR: OFFSET('Full Data'!$J$3,0,0,COUNTA('Full Data'!$I:$I)-1,1)

Sheet Full Data
A1: Advanced Business Intelligence Full Data | Y1: Advanced Business Intelligence Full Data
A2: OrderID | C2: Delivery days | D2: Region | E2: CustomerID | F2: Product | G2: Quantity | H2: UnitPrice | I2: Revenue | J2: {=_xlfn.XLOOKUP(F2,Products!A:A,Products!B:E)} -> Category | K2: UnitPrice | L2: UnitCost | M2: Discount | N2: Net Profit | O2: Ave DD | P2: Ave RR | Q2: Operational Efficiency | R2: Discounted rev | S2: Profit | T2: Classification | U2: pro details | V2: Dynamic Named Range | W2: Region | X2: order per region | Y2: Average Deli Time
A3: Q1-001 | B3: 45708.027 | C3: 5 | D3: South | E3: 1018 | F3: Tablet | G3: 1 | H3: 730 | I3: =G3*H3 -> 730 | J3: {=_xlfn.XLOOKUP(F3,Products!A:A,Products!B:E)} -> Electronics | K3: 1613 | L3: 492 | M3: 0.14 | N3: =Append1[[#This Row],[Revenue]]-(Finance_Data!B2+Finance_Data!C2+Finance_Data!D2) -> -106484 | O3: =Table10[[#Totals],[DeliveryDays]] -> 4.8888889 | P3: =Table10[[#Totals],[ReturnRate]] -> 0.050555556 | Q3: =1/(O3*(1+P3)) -> 0.19470218 | R3: =I3*(1-M3) -> 627.8 | S3: =I3-(G3*H3)-Finance_Data!B2 -> -25640 | T3: =IF(I3>50000,"VIP",IF(I3<20000,"Low Value",IF(B3>=20000-50000,"Regular"))) -> Low Value | U3: =INDEX('Full Data'!$K:$K,MATCH(F3,'Full Data'!$F:$F,0)) -> 1613 | V3: {=DNR} -> Electronics | W3: {=_xlfn.UNIQUE(D3:D92)} -> South | X3: =COUNTIF(D:D,"South") -> 23 | Y3: =AVERAGEIF($D:$D,"South",$C:$C) -> 5.4347826
A4: Q1-002 | B4: 45712.237 | C4: 2 | D4: South | E4: 1004 | F4: Headphones | G4: 3 | H4: 378 | I4: =G4*H4 -> 1134 | J4: {=_xlfn.XLOOKUP(F4,Products!A:A,Products!B:E)} -> Accessories | K4: 106 | L4: 323 | M4: 0.1 | N4: =Append1[[#This Row],[Revenue]]-(Finance_Data!B3+Finance_Data!C3+Finance_Data!D3) -> -140443 | O4: =Table10[[#Totals],[DeliveryDays]] -> 4.8888889 | P4: =Table10[[#Totals],[ReturnRate]] -> 0.050555556 | Q4: =1/(O4*(1+P4)) -> 0.19470218 | R4: =I4*(1-M4) -> 1020.6 | S4: =I4-(G4*H4)-Finance_Data!B3 -> -43320 | T4: =IF(I4>50000,"VIP",IF(I4<20000,"Low Value",IF(B4>=20000-50000,"Regular"))) -> Low Value | U4: =INDEX('Full Data'!$K:$K,MATCH(F4,'Full Data'!$F:$F,0)) -> 106 | V4: Accessories | W4: West | X4: =COUNTIF(D:D,"West") -> 24 | Y4: =AVERAGEIF($D:$D,"West",$C:$C) -> 5.0833333
A5: Q1-003 | B5: 45736.268 | C5: 6 | D5: West | E5: 1005 | F5: Monitor | G5: 1 | H5: 585 | I5: =G5*H5 -> 585 | J5: {=_xlfn.XLOOKUP(F5,Products!A:A,Products!B:E)} -> Electronics | K5: 396 | L5: 463 | M5: 0.23 | N5: =Append1[[#This Row],[Revenue]]-(Finance_Data!B4+Finance_Data!C4+Finance_Data!D4) -> -115190 | O5: =Table10[[#Totals],[DeliveryDays]] -> 4.8888889 | P5: =Table10[[#Totals],[ReturnRate]] -> 0.050555556 | Q5: =1/(O5*(1+P5)) -> 0.19470218 | R5: =I5*(1-M5) -> 450.45 | S5: =I5-(G5*H5)-Finance_Data!B4 -> -34147 | T5: =IF(I5>50000,"VIP",IF(I5<20000,"Low Value",IF(B5>=20000-50000,"Regular"))) -> Low Value | U5: =INDEX('Full Data'!$K:$K,MATCH(F5,'Full Data'!$F:$F,0)) -> 396 | V5: Electronics | W5: East | X5: =COUNTIF(D:D,"East") -> 21 | Y5: =AVERAGEIF($D:$D,"East",$C:$C) -> 4.3809524
A6: Q1-004 | B6: 45703.571 | C6: 4 | D6: East | E6: 1018 | F6: Smartphone | G6: 8 | H6: 726 | I6: =G6*H6 -> 5808 | J6: {=_xlfn.XLOOKUP(F6,Products!A:A,Products!B:E)} -> Electronics | K6: 1402 | L6: 97 | M6: 0.08 | N6: =Append1[[#This Row],[Revenue]]-(Finance_Data!B5+Finance_Data!C5+Finance_Data!D5) -> -150441 | O6: =Table10[[#Totals],[DeliveryDays]] -> 4.8888889 | P6: =Table10[[#Totals],[ReturnRate]] -> 0.050555556 | Q6: =1/(O6*(1+P6)) -> 0.19470218 | R6: =I6*(1-M6) -> 5343.36 | S6: =I6-(G6*H6)-Finance_Data!B5 -> -44423 | T6: =IF(I6>50000,"VIP",IF(I6<20000,"Low Value",IF(B6>=20000-50000,"Regular"))) -> Low Value | U6: =INDEX('Full Data'!$K:$K,MATCH(F6,'Full Data'!$F:$F,0)) -> 1402 | V6: Electronics | W6: North | X6: =COUNTIF(D:D,"North") -> 22 | Y6: =AVERAGEIF($D:$D,"North",$C:$C) -> 4.5909091
A7: Q1-005 | B7: 45663.686 | C7: 5 | D7: North | E7: 1012 | F7: Laptop | G7: 2 | H7: 709 | I7: =G7*H7 -> 1418 | J7: {=_xlfn.XLOOKUP(F7,Products!A:A,Products!B:E)} -> Electronics | K7: 1299 | L7: 469 | M7: 0.22 | N7: =Append1[[#This Row],[Revenue]]-(Finance_Data!B6+Finance_Data!C6+Finance_Data!D6) -> -106070 | O7: =Table10[[#Totals],[DeliveryDays]] -> 4.8888889 | P7: =Table10[[#Totals],[ReturnRate]] -> 0.050555556 | Q7: =1/(O7*(1+P7)) -> 0.19470218 | R7: =I7*(1-M7) -> 1106.04 | S7: =I7-(G7*H7)-Finance_Data!B6 -> -32119 | T7: =IF(I7>50000,"VIP",IF(I7<20000,"Low Value",IF(B7>=20000-50000,"Regular"))) -> Low Value | U7: =INDEX('Full Data'!$K:$K,MATCH(F7,'Full Data'!$F:$F,0)) -> 1299 | V7: Electronics
A8: Q1-006 | B8: 45716.227 | C8: 5 | D8: East | E8: 1013 | F8: Laptop | G8: 8 | H8: 1817 | I8: =G8*H8 -> 14536 | J8: {=_xlfn.XLOOKUP(F8,Products!A:A,Products!B:E)} -> Electronics | K8: 1299 | L8: 469 | M8: 0.22 | N8: =Append1[[#This Row],[Revenue]]-(Finance_Data!B7+Finance_Data!C7+Finance_Data!D7) -> -121266 | O8: =Table10[[#Totals],[DeliveryDays]] -> 4.8888889 | P8: =Table10[[#Totals],[ReturnRate]] -> 0.050555556 | Q8: =1/(O8*(1+P8)) -> 0.19470218 | R8: =I8*(1-M8) -> 11338.08 | S8: =I8-(G8*H8)-Finance_Data!B7 -> -20079 | T8: =IF(I8>50000,"VIP",IF(I8<20000,"Low Value",IF(B8>=20000-50000,"Regular"))) -> Low Value | U8: =INDEX('Full Data'!$K:$K,MATCH(F8,'Full Data'!$F:$F,0)) -> 1299 | V8: Electronics
A9: Q1-007 | B9: 45735.116 | C9: 4 | D9: South | E9: 1017 | F9: Tablet | G9: 9 | H9: 1976 | I9: =G9*H9 -> 17784 | J9: {=_xlfn.XLOOKUP(F9,Products!A:A,Products!B:E)} -> Electronics | K9: 1613 | L9: 492 | M9: 0.14 | N9: =Append1[[#This Row],[Revenue]]-(Finance_Data!B8+Finance_Data!C8+Finance_Data!D8) -> -107270 | O9: =Table10[[#Totals],[DeliveryDays]] -> 4.8888889 | P9: =Table10[[#Totals],[ReturnRate]] -> 0.050555556 | Q9: =1/(O9*(1+P9)) -> 0.19470218 | R9: =I9*(1-M9) -> 15294.24 | S9: =I9-(G9*H9)-Finance_Data!B8 -> -36304 | T9: =IF(I9>50000,"VIP",IF(I9<20000,"Low Value",IF(B9>=20000-50000,"Regular"))) -> Low Value | U9: =INDEX('Full Data'!$K:$K,MATCH(F9,'Full Data'!$F:$F,0)) -> 1613 | V9: Electronics
A10: Q1-008 | B10: 45707.394 | C10: 8 | D10: South | E10: 1014 | F10: Tablet | G10: 5 | H10: 1134 | I10: =G10*H10 -> 5670 | J10: {=_xlfn.XLOOKUP(F10,Products!A:A,Products!B:E)} -> Electronics | K10: 1613 | L10: 492 | M10: 0.14 | N10: =Append1[[#This Row],[Revenue]]-(Finance_Data!B9+Finance_Data!C9+Finance_Data!D9) -> -141054 | O10: =Table10[[#Totals],[DeliveryDays]] -> 4.8888889 | P10: =Table10[[#Totals],[ReturnRate]] -> 0.050555556 | Q10: =1/(O10*(1+P10)) -> 0.19470218 | R10: =I10*(1-M10) -> 4876.2 | S10: =I10-(G10*H10)-Finance_Data!B9 -> -36734 | T10: =IF(I10>50000,"VIP",IF(I10<20000,"Low Value",IF(B10>=20000-50000,"Regular"))) -> Low Value | U10: =INDEX('Full Data'!$K:$K,MATCH(F10,'Full Data'!$F:$F,0)) -> 1613 | V10: Electronics
A11: Q1-009 | B11: 45671.497 | C11: 2 | D11: South | E11: 1020 | F11: Printer | G11: 1 | H11: 1220 | I11: =G11*H11 -> 1220 | J11: {=_xlfn.XLOOKUP(F11,Products!A:A,Products!B:E)} -> Office | K11: 1635 | L11: 136 | M11: 0.1 | N11: =Append1[[#This Row],[Revenue]]-(Finance_Data!B10+Finance_Data!C10+Finance_Data!D10) -> -132618 | O11: =Table10[[#Totals],[DeliveryDays]] -> 4.8888889 | P11: =Table10[[#Totals],[ReturnRate]] -> 0.050555556 | Q11: =1/(O11*(1+P11)) -> 0.19470218 | R11: =I11*(1-M11) -> 1098 | S11: =I11-(G11*H11)-Finance_Data!B10 -> -34260 | T11: =IF(I11>50000,"VIP",IF(I11<20000,"Low Value",IF(B11>=20000-50000,"Regular"))) -> Low Value | U11: =INDEX('Full Data'!$K:$K,MATCH(F11,'Full Data'!$F:$F,0)) -> 1635 | V11: Office
A12: Q1-010 | B12: 45743.202 | C12: 2 | D12: West | E12: 1010 | F12: Headphones | G12: 2 | H12: 283 | I12: =G12*H12 -> 566 | J12: {=_xlfn.XLOOKUP(F12,Products!A:A,Products!B:E)} -> Accessories | K12: 106 | L12: 323 | M12: 0.1 | N12: =Append1[[#This Row],[Revenue]]-(Finance_Data!B11+Finance_Data!C11+Finance_Data!D11) -> 566 | O12: =Table10[[#Totals],[DeliveryDays]] -> 4.8888889 | P12: =Table10[[#Totals],[ReturnRate]] -> 0.050555556 | Q12: =1/(O12*(1+P12)) -> 0.19470218 | R12: =I12*(1-M12) -> 509.4 | S12: =I12-(G12*H12)-Finance_Data!B11 -> 0 | T12: =IF(I12>50000,"VIP",IF(I12<20000,"Low Value",IF(B12>=20000-50000,"Regular"))) -> Low Value | U12: =INDEX('Full Data'!$K:$K,MATCH(F12,'Full Data'!$F:$F,0)) -> 106 | V12: Accessories
A13: Q1-011 | B13: 45684.929 | C13: 8 | D13: West | E13: 1019 | F13: Laptop | G13: 9 | H13: 417 | I13: =G13*H13 -> 3753 | J13: {=_xlfn.XLOOKUP(F13,Products!A:A,Products!B:E)} -> Electronics | K13: 1299 | L13: 469 | M13: 0.22 | N13: =Append1[[#This Row],[Revenue]]-(Finance_Data!B12+Finance_Data!C12+Finance_Data!D12) -> 3753 | O13: =Table10[[#Totals],[DeliveryDays]] -> 4.8888889 | P13: =Table10[[#Totals],[ReturnRate]] -> 0.050555556 | Q13: =1/(O13*(1+P13)) -> 0.19470218 | R13: =I13*(1-M13) -> 2927.34 | S13: =I13-(G13*H13)-Finance_Data!B12 -> 0 | T13: =IF(I13>50000,"VIP",IF(I13<20000,"Low Value",IF(B13>=20000-50000,"Regular"))) -> Low Value | U13: =INDEX('Full Data'!$K:$K,MATCH(F13,'Full Data'!$F:$F,0)) -> 1299 | V13: Electronics
A14: Q1-012 | B14: 45662.79 | C14: 8 | D14: South | E14: 1016 | F14: Laptop | G14: 3 | H14: 1692 | I14: =G14*H14 -> 5076 | J14: {=_xlfn.XLOOKUP(F14,Products!A:A,Products!B:E)} -> Electronics | K14: 1299 | L14: 469 | M14: 0.22 | N14: =Append1[[#This Row],[Revenue]]-(Finance_Data!B13+Finance_Data!C13+Finance_Data!D13) -> 5076 | O14: =Table10[[#Totals],[DeliveryDays]] -> 4.8888889 | P14: =Table10[[#Totals],[ReturnRate]] -> 0.050555556 | Q14: =1/(O14*(1+P14)) -> 0.19470218 | R14: =I14*(1-M14) -> 3959.28 | S14: =I14-(G14*H14)-Finance_Data!B13 -> 0 | T14: =IF(I14>50000,"VIP",IF(I14<20000,"Low Value",IF(B14>=20000-50000,"Regular"))) -> Low Value | U14: =INDEX('Full Data'!$K:$K,MATCH(F14,'Full Data'!$F:$F,0)) -> 1299 | V14: Electronics
A15: Q1-013 | B15: 45693.46 | C15: 1 | D15: East | E15: 1001 | F15: Printer | G15: 4 | H15: 1853 | I15: =G15*H15 -> 7412 | J15: {=_xlfn.XLOOKUP(F15,Products!A:A,Products!B:E)} -> Office | K15: 1635 | L15: 136 | M15: 0.1 | N15: =Append1[[#This Row],[Revenue]]-(Finance_Data!B14+Finance_Data!C14+Finance_Data!D14) -> 7412 | O15: =Table10[[#Totals],[DeliveryDays]] -> 4.8888889 | P15: =Table10[[#Totals],[ReturnRate]] -> 0.050555556 | Q15: =1/(O15*(1+P15)) -> 0.19470218 | R15: =I15*(1-M15) -> 6670.8 | S15: =I15-(G15*H15)-Finance_Data!B14 -> 0 | T15: =IF(I15>50000,"VIP",IF(I15<20000,"Low Value",IF(B15>=20000-50000,"Regular"))) -> Low Value | U15: =INDEX('Full Data'!$K:$K,MATCH(F15,'Full Data'!$F:$F,0)) -> 1635 | V15: Office
A16: Q1-014 | B16: 45717.254 | C16: 3 | D16: South | E16: 1005 | F16: Printer | G16: 2 | H16: 505 | I16: =G16*H16 -> 1010 | J16: {=_xlfn.XLOOKUP(F16,Products!A:A,Products!B:E)} -> Office | K16: 1635 | L16: 136 | M16: 0.1 | N16: =Append1[[#This Row],[Revenue]]-(Finance_Data!B15+Finance_Data!C15+Finance_Data!D15) -> 1010 | O16: =Table10[[#Totals],[DeliveryDays]] -> 4.8888889 | P16: =Table10[[#Totals],[ReturnRate]] -> 0.050555556 | Q16: =1/(O16*(1+P16)) -> 0.19470218 | R16: =I16*(1-M16) -> 909 | S16: =I16-(G16*H16)-Finance_Data!B15 -> 0 | T16: =IF(I16>50000,"VIP",IF(I16<20000,"Low Value",IF(B16>=20000-50000,"Regular"))) -> Low Value | U16: =INDEX('Full Data'!$K:$K,MATCH(F16,'Full Data'!$F:$F,0)) -> 1635 | V16: Office
A17: Q1-015 | B17: 45672.073 | C17: 4 | D17: South | E17: 1016 | F17: Monitor | G17: 3 | H17: 1355 | I17: =G17*H17 -> 4065 | J17: {=_xlfn.XLOOKUP(F17,Products!A:A,Products!B:E)} -> Electronics | K17: 396 | L17: 463 | M17: 0.23 | N17: =Append1[[#This Row],[Revenue]]-(Finance_Data!B16+Finance_Data!C16+Finance_Data!D16) -> 4065 | O17: =Table10[[#Totals],[DeliveryDays]] -> 4.8888889 | P17: =Table10[[#Totals],[ReturnRate]] -> 0.050555556 | Q17: =1/(O17*(1+P17)) -> 0.19470218 | R17: =I17*(1-M17) -> 3130.05 | S17: =I17-(G17*H17)-Finance_Data!B16 -> 0 | T17: =IF(I17>50000,"VIP",IF(I17<20000,"Low Value",IF(B17>=20000-50000,"Regular"))) -> Low Value | U17: =INDEX('Full Data'!$K:$K,MATCH(F17,'Full Data'!$F:$F,0)) -> 396 | V17: Electronics
A18: Q1-016 | B18: 45742.873 | C18: 3 | D18: North | E18: 1003 | F18: Printer | G18: 8 | H18: 1220 | I18: =G18*H18 -> 9760 | J18: {=_xlfn.XLOOKUP(F18,Products!A:A,Products!B:E)} -> Office | K18: 1635 | L18: 136 | M18: 0.1 | N18: =Append1[[#This Row],[Revenue]]-(Finance_Data!B17+Finance_Data!C17+Finance_Data!D17) -> 9760 | O18: =Table10[[#Totals],[DeliveryDays]] -> 4.8888889 | P18: =Table10[[#Totals],[ReturnRate]] -> 0.050555556 | Q18: =1/(O18*(1+P18)) -> 0.19470218 | R18: =I18*(1-M18) -> 8784 | S18: =I18-(G18*H18)-Finance_Data!B17 -> 0 | T18: =IF(I18>50000,"VIP",IF(I18<20000,"Low Value",IF(B18>=20000-50000,"Regular"))) -> Low Value | U18: =INDEX('Full Data'!$K:$K,MATCH(F18,'Full Data'!$F:$F,0)) -> 1635 | V18: Office
... A92: Q3-030 | B92: 45898.259 | C92: 5 | D92: West | E92: 1003 | F92: Monitor | G92: 3 | H92: 651 | I92: =G92*H92 -> 1953 | J92: {=_xlfn.XLOOKUP(F92,Products!A:A,Products!B:E)} -> Electronics | K92: 396 | L92: 463 | M92: 0.23 | N92: =Append1[[#This Row],[Revenue]]-(Finance_Data!B91+Finance_Data!C91+Finance_Data!D91) -> 1953 | O92: =Table10[[#Totals],[DeliveryDays]] -> 4.8888889 | P92: =Table10[[#Totals],[ReturnRate]] -> 0.050555556 | Q92: =1/(O92*(1+P92)) -> 0.19470218 | R92: =I92*(1-M92) -> 1503.81 | S92: =I92-(G92*H92)-Finance_Data!B91 -> 0 | T92: =IF(I92>50000,"VIP",IF(I92<20000,"Low Value",IF(B92>=20000-50000,"Regular"))) -> Low Value | U92: =INDEX('Full Data'!$K:$K,MATCH(F92,'Full Data'!$F:$F,0)) -> 396 | V92: Electronics

Sheet Sales Data
A2: OrderID | B2: Date | C2: Region | D2: CustomerID | E2: Product | F2: Quantity | G2: UnitPrice | H2: Profit
A3: Q1-001 | B3: 45708.027 | C3: South | D3: 1018 | E3: Tablet | F3: 1 | G3: 730
A4: Q1-002 | B4: 45712.237 | C4: South | D4: 1004 | E4: Headphones | F4: 3 | G4: 378
A5: Q1-003 | B5: 45736.268 | C5: West | D5: 1005 | E5: Monitor | F5: 1 | G5: 585
A6: Q1-004 | B6: 45703.571 | C6: East | D6: 1018 | E6: Smartphone | F6: 8 | G6: 726
A7: Q1-005 | B7: 45663.686 | C7: North | D7: 1012 | E7: Laptop | F7: 2 | G7: 709
A8: Q1-006 | B8: 45716.227 | C8: East | D8: 1013 | E8: Laptop | F8: 8 | G8: 1817
A9: Q1-007 | B9: 45735.116 | C9: South | D9: 1017 | E9: Tablet | F9: 9 | G9: 1976
A10: Q1-008 | B10: 45707.394 | C10: South | D10: 1014 | E10: Tablet | F10: 5 | G10: 1134
A11: Q1-009 | B11: 45671.497 | C11: South | D11: 1020 | E11: Printer | F11: 1 | G11: 1220
A12: Q1-010 | B12: 45743.202 | C12: West | D12: 1010 | E12: Headphones | F12: 2 | G12: 283
A13: Q1-011 | B13: 45684.929 | C13: West | D13: 1019 | E13: Laptop | F13: 9 | G13: 417
A14: Q1-012 | B14: 45662.79 | C14: South | D14: 1016 | E14: Laptop | F14: 3 | G14: 1692
... A92: Q3-030 | B92: 45898.259 | C92: West | D92: 1003 | E92: Monitor | F92: 3 | G92: 651

Sheet Products
A1: Product | B1: Category | C1: UnitPrice | D1: UnitCost | E1: Discount
A2: Laptop | B2: Electronics | C2: 1299 | D2: 469 | E2: 0.22
A3: Tablet | B3: Electronics | C3: 1613 | D3: 492 | E3: 0.14
A4: Smartphone | B4: Electronics | C4: 1402 | D4: 97 | E4: 0.08
A5: Headphones | B5: Accessories | C5: 106 | D5: 323 | E5: 0.1
A6: Monitor | B6: Electronics | C6: 396 | D6: 463 | E6: 0.23
A7: Printer | B7: Office | C7: 1635 | D7: 136 | E7: 0.1

Sheet Finance_Data
A1: Month | B1: Overheads | C1: Salaries | D1: OtherExpenses
A2: 45688 | B2: 25640 | C2: 60082 | D2: 21492
A3: 45716 | B3: 43320 | C3: 70533 | D3: 27724
A4: 45747 | B4: 34147 | C4: 63890 | D4: 17738
A5: 45777 | B5: 44423 | C5: 90674 | D5: 21152
A6: 45808 | B6: 32119 | C6: 55646 | D6: 19723
A7: 45838 | B7: 20079 | C7: 99954 | D7: 15769
A8: 45869 | B8: 36304 | C8: 63297 | D8: 25453
A9: 45900 | B9: 36734 | C9: 93760 | D9: 16230
A10: 45930 | B10: 34260 | C10: 70760 | D10: 28818

Sheet Operational_Data
A1: OrderID | B1: DeliveryDays | C1: ReturnRate
A2: Q1-001 | B2: 5 | C2: 0.01
A3: Q1-002 | B3: 2 | C3: 0.03
A4: Q1-003 | B4: 6 | C4: 0.05
A5: Q1-004 | B5: 4 | C5: 0.07
A6: Q1-005 | B6: 5 | C6: 0.03
A7: Q1-006 | B7: 5 | C7: 0.06
A8: Q1-007 | B8: 4 | C8: 0.02
A9: Q1-008 | B9: 8 | C9: 0.07
A10: Q1-009 | B10: 2 | C10: 0.08
A11: Q1-010 | B11: 2 | C11: 0.08
A12: Q1-011 | B12: 8 | C12: 0.06
A13: Q1-012 | B13: 8 | C13: 0.03
... A91: Q3-030 | B91: 5 | C91: 0.09
A92: Total | B92: =SUBTOTAL(101,Table10[DeliveryDays]) -> 4.8888889 | C92: =SUBTOTAL(101,Table10[ReturnRate]) -> 0.050555556

Sheet Customer_List
A1: CustomerID | B1: FirstName | C1: LastName | D1: Email | E1: Region | F1: Standard name
A2: 1001 | B2: Naledi | C2: Pillay | D2: naledi.pillay@example.com | E2: East | F2: {=PROPER(B2:C29)} -> Naledi | G2: Pillay
A3: 1002 | B3: Michael | C3: van Wyk | D3: michael.van wyk@example.com | E3: East | F3: Michael | G3: Van Wyk
A4: 1003 | B4: Naledi | C4: Botha | D4: naledi.botha@example.com | E4: East | F4: Naledi | G4: Botha
A5: 1004 | B5: Naledi | C5: Botha | D5: naledi.botha@example.com | E5: North | F5: Naledi | G5: Botha
A6: 1005 | B6: Michael | C6: Johnson | D6: michael.johnson@example.com | E6: North | F6: Michael | G6: Johnson
A7: 1006 | B7: Emily | C7: Johnson | D7: emily.johnson@example.com | E7: South | F7: Emily | G7: Johnson
A8: 1007 | B8: Michael | C8: Nguyen | D8: michael.nguyen@example.com | E8: West | F8: Michael | G8: Nguyen
A9: 1008 | B9: Sipho | C9: Johnson | D9: sipho.johnson@example.com | E9: East | F9: Sipho | G9: Johnson
A10: 1009 | B10: Sarah | C10: Nguyen | D10: sarah.nguyen@example.com | E10: North | F10: Sarah | G10: Nguyen
A11: 1010 | B11: John | C11: Brown | D11: john.brown@example.com | E11: East | F11: John | G11: Brown
A12: 1011 | B12: John | C12: Smith | D12: john.smith@example.com | E12: South | F12: John | G12: Smith
A13: 1012 | B13: Naledi | C13: van Wyk | D13: naledi.van wyk@example.com | E13: East | F13: Naledi | G13: Van Wyk
A14: 1013 | B14: Sipho | C14: van Wyk | D14: sipho.van wyk@example.com | E14: South | F14: Sipho | G14: Van Wyk
... A29: 1018 | B29: Michael | C29: Mlambo | D29: michael.mlambo@example.com | E29: South | F29: Michael | G29: Mlambo
